lactopy/__init__.py
lactopy/py.typed
lactopy/lactate_models/__init__.py
lactopy/lactate_models/base/__init__.py
lactopy/lactate_models/base/base.py
lactopy/lactate_models/base/adaptors/__init__.py
lactopy/lactate_models/base/adaptors/cubicAdaptors.py
lactopy/lactate_models/base/adaptors/polyAdapter.py
lactopy/lactate_models/first_threshold/__init__.py
lactopy/lactate_models/general/OBLA.py
lactopy/lactate_models/general/__init__.py
lactopy/lactate_models/general/bsln.py
lactopy/lactate_models/second_threshold/__init__.py
lactopy/lactate_models/second_threshold/dmax.py
lactopy/plots/__init__.py
lactopy/plots/base.py
lactopy-0.1.0.dist-info/METADATA
lactopy-0.1.0.dist-info/WHEEL
lactopy-0.1.0.dist-info/licenses/LICENSE
lactopy-0.1.0.dist-info/RECORD
